cde_diagnostics/__init__.py
cde_diagnostics/classifiers.py
cde_diagnostics/global_test.py
cde_diagnostics/local_histogram.py
cde_diagnostics/local_plot.py
cde_diagnostics/local_pp_plot.py
cde_diagnostics/local_test.py
cde_diagnostics-0.3.dist-info/LICENSE
cde_diagnostics-0.3.dist-info/METADATA
cde_diagnostics-0.3.dist-info/WHEEL
cde_diagnostics-0.3.dist-info/top_level.txt
cde_diagnostics-0.3.dist-info/RECORD
