Metadata-Version: 2.1
Name: cde-diagnostics
Version: 0.3
Summary: Diagnostics for conditional density estimators locally and globally in feature space
Home-page: https://github.com/zhao-david/CDE-diagnostics
Author: David Zhao
Author-email: davidzhao@cmu.edu
Maintainer: davidzhao@cmu.edu
License: MIT
Keywords: conditional density estimator,permutation test
Platform: UNKNOWN
Classifier: License :: OSI Approved :: MIT License
Classifier: Topic :: Scientific/Engineering :: Artificial Intelligence
Classifier: Programming Language :: Python :: 2.7
Classifier: Programming Language :: Python :: 3.6
Requires-Python: >=2.7
License-File: LICENSE
Requires-Dist: numpy
Requires-Dist: scipy
Requires-Dist: sklearn
